scrapy_do/__init__.py
scrapy_do/app.py
scrapy_do/config.py
scrapy_do/controller.py
scrapy_do/default.conf
scrapy_do/schedule.py
scrapy_do/utils.py
scrapy_do/webservice.py
scrapy_do/websocket.py
scrapy_do/client/__init__.py
scrapy_do/client/archive.py
scrapy_do/client/commands.py
scrapy_do/client/webclient.py
scrapy_do/ui/asset-manifest.json
scrapy_do/ui/favicon.png
scrapy_do/ui/index.html
scrapy_do/ui/manifest.json
scrapy_do/ui/precache-manifest.b07bf6aa92181b2b8ecfbd20c7e653f7.js
scrapy_do/ui/scrapy-do-logo.png
scrapy_do/ui/service-worker.js
scrapy_do/ui/static/css/2.d194689a.chunk.css
scrapy_do/ui/static/css/2.d194689a.chunk.css.map
scrapy_do/ui/static/css/main.91a93399.chunk.css
scrapy_do/ui/static/css/main.91a93399.chunk.css.map
scrapy_do/ui/static/js/2.0129959e.chunk.js
scrapy_do/ui/static/js/2.0129959e.chunk.js.LICENSE.txt
scrapy_do/ui/static/js/2.0129959e.chunk.js.map
scrapy_do/ui/static/js/main.fcf8f966.chunk.js
scrapy_do/ui/static/js/main.fcf8f966.chunk.js.map
scrapy_do/ui/static/js/runtime-main.4c1ec1e9.js
scrapy_do/ui/static/js/runtime-main.4c1ec1e9.js.map
scrapy_do_heroku-0.4.1.data/scripts/scrapy-do
scrapy_do_heroku-0.4.1.data/scripts/scrapy-do-cl
scrapy_do_heroku-0.4.1.dist-info/LICENSE
scrapy_do_heroku-0.4.1.dist-info/METADATA
scrapy_do_heroku-0.4.1.dist-info/WHEEL
scrapy_do_heroku-0.4.1.dist-info/top_level.txt
scrapy_do_heroku-0.4.1.dist-info/RECORD
