Metadata-Version: 2.1
Name: scrapy-do-heroku
Version: 0.4.1
Summary: A daemon for scheduling Scrapy spiders
Home-page: UNKNOWN
Author: Ahmed Rafik
Author-email: djerahahmedrafik@mail.com
License: BSD License
Platform: UNKNOWN
Classifier: Framework :: Scrapy
Classifier: Development Status :: 4 - Beta
Classifier: Intended Audience :: Developers
Classifier: License :: OSI Approved :: BSD License
Classifier: Operating System :: OS Independent
Classifier: Programming Language :: Python
Classifier: Programming Language :: Python :: 3
Classifier: Programming Language :: Python :: 3.7
Classifier: Topic :: Internet :: WWW/HTTP
Classifier: Environment :: Console
Classifier: Environment :: No Input/Output (Daemon)
Requires-Dist: autobahn
Requires-Dist: pem
Requires-Dist: psutil
Requires-Dist: pyOpenSSL
Requires-Dist: python-dateutil
Requires-Dist: requests
Requires-Dist: schedule
Requires-Dist: scrapy
Requires-Dist: tabulate
Requires-Dist: twisted
Requires-Dist: tzlocal
